ckeditor_skins/__init__.py
ckeditor_skins/apps.py
ckeditor_skins/static/ckeditor/ckeditor/skins/moono-dark/dialog.css
ckeditor_skins/static/ckeditor/ckeditor/skins/moono-dark/dialog_ie.css
ckeditor_skins/static/ckeditor/ckeditor/skins/moono-dark/dialog_ie7.css
ckeditor_skins/static/ckeditor/ckeditor/skins/moono-dark/dialog_ie8.css
ckeditor_skins/static/ckeditor/ckeditor/skins/moono-dark/dialog_iequirks.css
ckeditor_skins/static/ckeditor/ckeditor/skins/moono-dark/editor.css
ckeditor_skins/static/ckeditor/ckeditor/skins/moono-dark/editor_gecko.css
ckeditor_skins/static/ckeditor/ckeditor/skins/moono-dark/editor_ie.css
ckeditor_skins/static/ckeditor/ckeditor/skins/moono-dark/editor_ie7.css
ckeditor_skins/static/ckeditor/ckeditor/skins/moono-dark/editor_ie8.css
ckeditor_skins/static/ckeditor/ckeditor/skins/moono-dark/editor_iequirks.css
ckeditor_skins/static/ckeditor/ckeditor/skins/moono-dark/icons.png
ckeditor_skins/static/ckeditor/ckeditor/skins/moono-dark/icons_hidpi.png
ckeditor_skins/static/ckeditor/ckeditor/skins/moono-dark/readme.md
ckeditor_skins/static/ckeditor/ckeditor/skins/moono-dark/skin.js
ckeditor_skins/static/ckeditor/ckeditor/skins/moono-dark/images/arrow.png
ckeditor_skins/static/ckeditor/ckeditor/skins/moono-dark/images/close.png
ckeditor_skins/static/ckeditor/ckeditor/skins/moono-dark/images/lock-open.png
ckeditor_skins/static/ckeditor/ckeditor/skins/moono-dark/images/lock.png
ckeditor_skins/static/ckeditor/ckeditor/skins/moono-dark/images/refresh.png
ckeditor_skins/static/ckeditor/ckeditor/skins/moono-dark/images/hidpi/close.png
ckeditor_skins/static/ckeditor/ckeditor/skins/moono-dark/images/hidpi/lock-open.png
ckeditor_skins/static/ckeditor/ckeditor/skins/moono-dark/images/hidpi/lock.png
ckeditor_skins/static/ckeditor/ckeditor/skins/moono-dark/images/hidpi/refresh.png
ckeditor_skins/static/ckeditor/ckeditor/skins/prestige/README.md
ckeditor_skins/static/ckeditor/ckeditor/skins/prestige/blue.png
django_ckeditor_skins-0.0.2.dist-info/LICENSE
django_ckeditor_skins-0.0.2.dist-info/METADATA
django_ckeditor_skins-0.0.2.dist-info/WHEEL
django_ckeditor_skins-0.0.2.dist-info/top_level.txt
django_ckeditor_skins-0.0.2.dist-info/RECORD
